{"is_source_file": true, "format": "Python", "description": "A simple script to run a Flask application by invoking app.run() if executed as main.", "external_files": ["app"], "external_methods": ["app.run"], "published": [], "classes": [], "methods": [], "calls": ["app.run"], "search-terms": ["run.py", "Flask app", "main execution", "app.run"], "state": 2, "file_id": 2, "knowledge_revision": 10, "git_revision": "15e3070a5860c0c5600696b16715bb1a046d2ed1", "ctags": [], "hash": "b4cfd2f2017c7f88e4049fa0ed026e86", "format-version": 4, "code-base-name": "ChatService", "filename": "ChatService/run.py", "revision_history": [{"10": "15e3070a5860c0c5600696b16715bb1a046d2ed1"}]}